{
    "type": "Apartment",
    "uri": "http://schema4i.org/Apartment",
    "description": "An apartment (in American English) or flat (in British English) is a self-contained housing unit (a type of residential real estate) that occupies only part of a building.",
    "links": [{
        "url": "http://schema.org/Apartment",
        "description": "Original Schema.org type"
    }],
    "parents": [],
    "base": [
        { "@id": "http://schema4i.org/Accommodation" }
    ],
    "multipletypes": {},
    "context": {
        "@context": {
            "@version": 1.1,
            "s4i": "http://schema4i.org/",
            "schema": "http://schema.org/",
            "Apartment": "schema:Apartment"
        }
    },
    "playground": [{
        "title": "A maximum Apartment",
        "tab": "tab-expanded",
        "input": {
            "@context": {},
            "@type": "Apartment"
        },
        "context": {}
    }]
}